pPEGpy/__init__.py
pPEGpy/peg.py
pPEGpy/py.typed
ppegpy-0.3.17.dist-info/METADATA
ppegpy-0.3.17.dist-info/WHEEL
ppegpy-0.3.17.dist-info/licenses/LICENSE
ppegpy-0.3.17.dist-info/RECORD
