Metadata-Version: 2.4
Name: pPEGpy
Version: 0.3.17
Summary: pPEG -- portable PEG in Python
Author-email: Peter Cashin <cashin.peter@gmail.com>
License-File: LICENSE
Requires-Python: >=3.10
